{"v":"5.9.6","fr":25,"ip":0,"op":750,"w":500,"h":500,"nm":"Graduation","ddd":0,"assets":[],"layers":[{"ddd":0,"ind":1,"ty":1,"nm":"CONTROLS","sr":1,"ks":{"o":{"a":0,"k":0,"ix":11},"r":{"a":0,"k":0,"ix":10},"p":{"a":0,"k":[250,250,0],"ix":2,"l":2},"a":{"a":0,"k":[250,250,0],"ix":1,"l":2},"s":{"a":0,"k":[100,100,100],"ix":6,"l":2}},"ao":0,"ef":[{"ty":5,"nm":"Color_1","np":3,"mn":"ADBE Color Control","ix":1,"en":1,"ef":[{"ty":2,"nm":"Color","mn":"ADBE Color Control-0001","ix":1,"v":{"a":0,"k":[0.98431378603,0.976470649242,0.525490224361,1],"ix":1}}]},{"ty":5,"nm":"Color_2","np":3,"mn":"ADBE Color Control","ix":2,"en":1,"ef":[{"ty":2,"nm":"Color","mn":"ADBE Color Control-0001","ix":1,"v":{"a":0,"k":[0.098039224744,0.086274512112,0.309803932905,1],"ix":1}}]}],"sw":500,"sh":500,"sc":"#000000","ip":0,"op":750,"st":0,"bm":0},{"ddd":0,"ind":2,"ty":4,"nm":"Isolation Mode 3","parent":3,"sr":1,"ks":{"o":{"a":0,"k":100,"ix":11},"r":{"a":0,"k":0,"ix":10},"p":{"a":0,"k":[5.653,86.577,0],"ix":2,"l":2},"a":{"a":0,"k":[5.653,86.577,0],"ix":1,"l":2},"s":{"a":0,"k":[100,100,100],"ix":6,"l":2}},"ao":0,"ef":[{"ty":21,"nm":"Fill","np":9,"mn":"ADBE Fill","ix":1,"en":1,"ef":[{"ty":10,"nm":"Fill Mask","mn":"ADBE Fill-0001","ix":1,"v":{"a":0,"k":0,"ix":1}},{"ty":7,"nm":"All Masks","mn":"ADBE Fill-0007","ix":2,"v":{"a":0,"k":0,"ix":2}},{"ty":2,"nm":"Color","mn":"ADBE Fill-0002","ix":3,"v":{"a":0,"k":[1,1,1,1],"ix":3,"x":"var $bm_rt;\n$bm_rt = thisComp.layer('CONTROLS').effect('Color_1')('ADBE Color Control-0001');"}},{"ty":7,"nm":"Invert","mn":"ADBE Fill-0006","ix":4,"v":{"a":0,"k":0,"ix":4}},{"ty":0,"nm":"Horizontal Feather","mn":"ADBE Fill-0003","ix":5,"v":{"a":0,"k":0,"ix":5}},{"ty":0,"nm":"Vertical Feather","mn":"ADBE Fill-0004","ix":6,"v":{"a":0,"k":0,"ix":6}},{"ty":0,"nm":"Opacity","mn":"ADBE Fill-0005","ix":7,"v":{"a":0,"k":1,"ix":7}}]}],"shapes":[{"ty":"gr","it":[{"ind":0,"ty":"sh","ix":1,"ks":{"a":0,"k":{"i":[[8.017,-0.622],[35.956,1.865],[0,6.694],[1.642,5.754],[-27.86,8.256],[0,-19.604]],"o":[[-27.86,-8.256],[1.562,-5.754],[0,-6.535],[35.956,-2.024],[8.017,0.478],[0,19.763]],"v":[[137.214,93.555],[39.004,78.302],[41.411,59.464],[38.924,40.944],[137.214,25.531],[153.87,59.464]],"c":true},"ix":2},"nm":"Path 1","mn":"ADBE Vector Shape - Group","hd":false},{"ind":1,"ty":"sh","ix":2,"ks":{"a":0,"k":{"i":[[-28.099,-1.403],[0,-6.694],[1.785,-5.291],[24.13,-5.132],[0,11.061],[3.905,7.778]],"o":[[1.944,5.61],[0,7.013],[-28.258,1.403],[3.905,-7.618],[0,-10.886],[24.051,5.291]],"v":[[-24.653,40.944],[-21.625,59.464],[-24.414,78.143],[-104.04,87.945],[-97.809,59.464],[-104.04,30.982]],"c":true},"ix":2},"nm":"Path 4","mn":"ADBE Vector Shape - Group","hd":false},{"ind":2,"ty":"sh","ix":3,"ks":{"a":0,"k":{"i":[[0,0],[0,0],[1.243,-0.478],[0,0],[0,0],[-13.93,-0.622]],"o":[[0,0],[-1.243,-0.478],[0,0],[0,0],[13.93,-0.622],[0,0]],"v":[[26.636,145.226],[7.558,137.608],[3.669,137.608],[-15.313,145.226],[-15.313,88.264],[26.636,88.264]],"c":true},"ix":2},"nm":"Path 2","mn":"ADBE Vector Shape - Group","hd":false},{"ty":"fl","c":{"a":0,"k":[0.101960785687,0.090196080506,0.105882354081,1],"ix":4},"o":{"a":0,"k":100,"ix":5},"r":1,"bm":0,"nm":"Fill 1","mn":"ADBE Vector Graphic - Fill","hd":false},{"ty":"tr","p":{"a":0,"k":[0,0],"ix":2},"a":{"a":0,"k":[0,0],"ix":1},"s":{"a":0,"k":[100,100],"ix":3},"r":{"a":0,"k":0,"ix":6},"o":{"a":0,"k":100,"ix":7},"sk":{"a":0,"k":0,"ix":4},"sa":{"a":0,"k":0,"ix":5},"nm":"Transform"}],"nm":"Group 1","np":4,"cix":2,"bm":0,"ix":1,"mn":"ADBE Vector Group","hd":false}],"ip":5,"op":755,"st":5,"ct":1,"bm":0},{"ddd":0,"ind":3,"ty":4,"nm":"Isolation Mode 2","sr":1,"ks":{"o":{"a":0,"k":100,"ix":11},"r":{"a":0,"k":0,"ix":10},"p":{"a":0,"k":[255.653,264.949,0],"ix":2,"l":2},"a":{"a":0,"k":[5.653,14.949,0],"ix":1,"l":2},"s":{"a":1,"k":[{"i":{"x":[0.833,0.833,0.833],"y":[0.833,0.833,0.833]},"o":{"x":[0.167,0.167,0.167],"y":[0.167,0.167,0.167]},"t":5,"s":[0,0,100]},{"t":30,"s":[100,100,100]}],"ix":6,"l":2,"x":"var $bm_rt;\nfunction easeandwizz_outElastic(t, b, c, d, a, p) {\n    var s;\n    var p = 0.81;\n    var a = 50;\n    if (t == 0)\n        return b;\n    if ((t /= d) == 1)\n        return $bm_sum(b, c);\n    if (!p)\n        p = $bm_mul(d, 0.3);\n    if (!a || a < Math.abs(c)) {\n        a = c;\n        s = $bm_div(p, 4);\n    } else\n        s = $bm_mul($bm_div(p, $bm_mul(2, Math.PI)), Math.asin($bm_div(c, a)));\n    return $bm_sum($bm_sum($bm_mul($bm_mul(a, Math.pow(2, $bm_mul(-10, t))), Math.sin($bm_div($bm_mul($bm_sub($bm_mul(t, d), s), $bm_mul(2, Math.PI)), p))), c), b);\n}\nfunction easeAndWizz() {\n    var t, d, sX, eX, sY, eY, sZ, eZ, val1, val2, val2, val3;\n    var n = 0;\n    if (numKeys > 0) {\n        n = nearestKey(time).index;\n        if (key(n).time > time) {\n            n--;\n        }\n    }\n    try {\n        var key1 = key(n);\n        var key2 = key($bm_sum(n, 1));\n    } catch (e) {\n        return null;\n    }\n    var dim = 1;\n    try {\n        key(1)[1].length;\n        dim = 2;\n        key(1)[2].length;\n        dim = 3;\n    } catch (e) {\n    }\n    t = $bm_sub(time, key1.time);\n    d = $bm_sub(key2.time, key1.time);\n    sX = key1[0];\n    eX = $bm_sub(key2[0], key1[0]);\n    if (dim >= 2) {\n        sY = key1[1];\n        eY = $bm_sub(key2[1], key1[1]);\n        if (dim >= 3) {\n            sZ = key1[2];\n            eZ = $bm_sub(key2[2], key1[2]);\n        }\n    }\n    if (time < key1.time || time > key2.time) {\n        return value;\n    } else {\n        val1 = easeandwizz_outElastic(t, sX, eX, d);\n        switch (dim) {\n        case 1:\n            return val1;\n            break;\n        case 2:\n            val2 = easeandwizz_outElastic(t, sY, eY, d);\n            return [\n                val1,\n                val2\n            ];\n            break;\n        case 3:\n            val2 = easeandwizz_outElastic(t, sY, eY, d);\n            val3 = easeandwizz_outElastic(t, sZ, eZ, d);\n            return [\n                val1,\n                val2,\n                val3\n            ];\n            break;\n        default:\n            return null;\n        }\n    }\n}\n$bm_rt = easeAndWizz() || value;"}},"ao":0,"ef":[{"ty":21,"nm":"Fill","np":9,"mn":"ADBE Fill","ix":1,"en":1,"ef":[{"ty":10,"nm":"Fill Mask","mn":"ADBE Fill-0001","ix":1,"v":{"a":0,"k":0,"ix":1}},{"ty":7,"nm":"All Masks","mn":"ADBE Fill-0007","ix":2,"v":{"a":0,"k":0,"ix":2}},{"ty":2,"nm":"Color","mn":"ADBE Fill-0002","ix":3,"v":{"a":0,"k":[1,1,1,1],"ix":3,"x":"var $bm_rt;\n$bm_rt = thisComp.layer('CONTROLS').effect('Color_2')('ADBE Color Control-0001');"}},{"ty":7,"nm":"Invert","mn":"ADBE Fill-0006","ix":4,"v":{"a":0,"k":0,"ix":4}},{"ty":0,"nm":"Horizontal Feather","mn":"ADBE Fill-0003","ix":5,"v":{"a":0,"k":0,"ix":5}},{"ty":0,"nm":"Vertical Feather","mn":"ADBE Fill-0004","ix":6,"v":{"a":0,"k":0,"ix":6}},{"ty":0,"nm":"Opacity","mn":"ADBE Fill-0005","ix":7,"v":{"a":0,"k":1,"ix":7}}]}],"shapes":[{"ty":"gr","it":[{"ind":0,"ty":"sh","ix":1,"ks":{"a":0,"k":{"i":[[8.017,-0.622],[35.956,1.865],[0,6.694],[1.642,5.754],[-27.86,8.256],[0,-19.604]],"o":[[-27.86,-8.256],[1.562,-5.754],[0,-6.535],[35.956,-2.024],[8.017,0.478],[0,19.763]],"v":[[137.214,93.555],[39.004,78.302],[41.411,59.464],[38.924,40.944],[137.214,25.531],[153.87,59.464]],"c":true},"ix":2},"nm":"Path 1","mn":"ADBE Vector Shape - Group","hd":false},{"ind":1,"ty":"sh","ix":2,"ks":{"a":0,"k":{"i":[[0,0],[0,0],[1.243,-0.478],[0,0],[0,0],[-13.93,-0.622]],"o":[[0,0],[-1.243,-0.478],[0,0],[0,0],[13.93,-0.622],[0,0]],"v":[[26.636,145.226],[7.558,137.608],[3.669,137.608],[-15.313,145.226],[-15.313,88.264],[26.636,88.264]],"c":true},"ix":2},"nm":"Path 2","mn":"ADBE Vector Shape - Group","hd":false},{"ind":2,"ty":"sh","ix":3,"ks":{"a":0,"k":{"i":[[0,19.763],[-7.953,0.478],[-1.721,-0.462],[0,-16.177],[6.614,-4.048],[1.705,-0.462]],"o":[[0,-19.604],[1.705,0.478],[6.614,4.048],[0,16.352],[-1.721,0.462],[-7.953,-0.622]],"v":[[-142.627,59.464],[-125.971,25.531],[-120.839,26.934],[-108.312,59.464],[-120.839,92.153],[-125.971,93.555]],"c":true},"ix":2},"nm":"Path 3","mn":"ADBE Vector Shape - Group","hd":false},{"ind":3,"ty":"sh","ix":4,"ks":{"a":0,"k":{"i":[[-28.099,-1.403],[0,-6.694],[1.785,-5.291],[24.13,-5.132],[0,11.061],[3.905,7.778]],"o":[[1.944,5.61],[0,7.013],[-28.258,1.403],[3.905,-7.618],[0,-10.886],[24.051,5.291]],"v":[[-24.653,40.944],[-21.625,59.464],[-24.414,78.143],[-104.04,87.945],[-97.809,59.464],[-104.04,30.982]],"c":true},"ix":2},"nm":"Path 4","mn":"ADBE Vector Shape - Group","hd":false},{"ind":4,"ty":"sh","ix":5,"ks":{"a":0,"k":{"i":[[-7.395,0.303],[0,-6.535],[1.801,-5.451],[13.85,-0.462],[0,6.535],[1.562,5.77],[-6.375,0]],"o":[[1.865,5.435],[0,6.694],[-13.771,-0.622],[1.482,-5.61],[0,-6.375],[6.391,0.319],[7.555,0]],"v":[[28.039,41.262],[30.907,59.464],[28.182,77.84],[-13.369,77.681],[-11.105,59.464],[-13.528,41.406],[5.614,41.725]],"c":true},"ix":2},"nm":"Path 5","mn":"ADBE Vector Shape - Group","hd":false},{"ind":5,"ty":"sh","ix":6,"ks":{"a":0,"k":{"i":[[15.173,0.622],[0,0],[0.159,0],[0.239,0],[0.319,0],[71.833,19.46],[3.028,0],[0.143,0],[0,0],[0,-24.592],[-15.189,-0.462],[-0.064,-0.159],[-0.159,0],[-2.725,1.403],[-33.008,1.721],[0,0],[-1.403,-1.1],[-1.642,0.622],[0,0],[0,0],[-0.622,0],[-0.924,0.462],[0,1.562],[0,0],[-27.7,-8.24],[-0.542,0],[0,0],[0,25.055]],"o":[[-0.08,0],[-0.239,0],[-0.319,0],[-0.239,0],[-69.108,20.863],[-2.725,-1.403],[-0.239,0],[0,0],[-15.189,0.622],[0,24.752],[0,0],[0.159,0],[3.028,0],[26.378,-7.156],[0,0],[0,1.562],[1.482,0.924],[0,0],[0,0],[0.622,0.159],[1.084,0],[1.403,-1.1],[0,0],[35.956,1.881],[0.542,0.159],[0,0],[15.492,0],[0,-24.592]],"v":[[137.374,14.949],[137.294,14.949],[136.752,14.949],[135.971,15.108],[135.19,15.108],[-116.791,17.132],[-125.429,14.949],[-125.971,14.949],[-126.051,14.949],[-153.066,59.464],[-126.051,103.979],[-125.908,104.138],[-125.429,104.138],[-116.791,101.955],[-25.816,88.567],[-25.816,153.004],[-23.569,157.371],[-18.58,157.834],[5.614,148.032],[29.903,157.834],[31.848,158.152],[34.796,157.371],[37.139,153.004],[37.139,88.567],[135.19,103.819],[136.752,104.138],[136.752,104.138],[164.373,59.464]],"c":true},"ix":2},"nm":"Path 6","mn":"ADBE Vector Shape - Group","hd":false},{"ty":"fl","c":{"a":0,"k":[0.101960785687,0.090196080506,0.105882354081,1],"ix":4},"o":{"a":0,"k":100,"ix":5},"r":1,"bm":0,"nm":"Fill 1","mn":"ADBE Vector Graphic - Fill","hd":false},{"ty":"tr","p":{"a":0,"k":[0,0],"ix":2},"a":{"a":0,"k":[0,0],"ix":1},"s":{"a":0,"k":[100,100],"ix":3},"r":{"a":0,"k":0,"ix":6},"o":{"a":0,"k":100,"ix":7},"sk":{"a":0,"k":0,"ix":4},"sa":{"a":0,"k":0,"ix":5},"nm":"Transform"}],"nm":"Group 1","np":7,"cix":2,"bm":0,"ix":1,"mn":"ADBE Vector Group","hd":false}],"ip":5,"op":755,"st":5,"ct":1,"bm":0},{"ddd":0,"ind":4,"ty":4,"nm":"Isolation Mode 4","parent":5,"sr":1,"ks":{"o":{"a":0,"k":100,"ix":11},"r":{"a":0,"k":0,"ix":10},"p":{"a":0,"k":[3.25,-72.115,0],"ix":2,"l":2},"a":{"a":0,"k":[5,-71.085,0],"ix":1,"l":2},"s":{"a":0,"k":[104.167,104.167,100],"ix":6,"l":2}},"ao":0,"ef":[{"ty":21,"nm":"Fill","np":9,"mn":"ADBE Fill","ix":1,"en":1,"ef":[{"ty":10,"nm":"Fill Mask","mn":"ADBE Fill-0001","ix":1,"v":{"a":0,"k":0,"ix":1}},{"ty":7,"nm":"All Masks","mn":"ADBE Fill-0007","ix":2,"v":{"a":0,"k":0,"ix":2}},{"ty":2,"nm":"Color","mn":"ADBE Fill-0002","ix":3,"v":{"a":0,"k":[1,1,1,1],"ix":3,"x":"var $bm_rt;\n$bm_rt = thisComp.layer('CONTROLS').effect('Color_1')('ADBE Color Control-0001');"}},{"ty":7,"nm":"Invert","mn":"ADBE Fill-0006","ix":4,"v":{"a":0,"k":0,"ix":4}},{"ty":0,"nm":"Horizontal Feather","mn":"ADBE Fill-0003","ix":5,"v":{"a":0,"k":0,"ix":5}},{"ty":0,"nm":"Vertical Feather","mn":"ADBE Fill-0004","ix":6,"v":{"a":0,"k":0,"ix":6}},{"ty":0,"nm":"Opacity","mn":"ADBE Fill-0005","ix":7,"v":{"a":0,"k":1,"ix":7}}]}],"shapes":[{"ty":"gr","it":[{"ind":0,"ty":"sh","ix":1,"ks":{"a":0,"k":{"i":[[0,0],[0,0],[0,0],[20.48,-5.148],[0,0],[0,0]],"o":[[0,0],[0,0],[-0.159,6.216],[0,0],[0,0],[0,0]],"v":[[86.165,-73.604],[86.165,-73.604],[86.165,-68.934],[54.018,-49.633],[54.018,-74.082],[86.165,-81.397]],"c":true},"ix":2},"nm":"Path 2","mn":"ADBE Vector Shape - Group","hd":false},{"ind":1,"ty":"sh","ix":2,"ks":{"a":0,"k":{"i":[[0,0],[-0.383,0],[-0.398,0.159],[0,0],[0,0],[14.551,0],[0,10.424],[0,0],[0,0]],"o":[[0.383,0.159],[0.398,0],[0,0],[0,0],[-11.045,2.024],[-50.269,0],[0,0],[0,0],[0,0]],"v":[[3.829,-63.18],[4.992,-63.021],[6.171,-63.18],[43.514,-71.739],[43.514,-47.465],[4.992,-44.198],[-76.165,-69.093],[-76.165,-72.201],[-76.165,-81.397]],"c":true},"ix":2},"nm":"Path 6","mn":"ADBE Vector Shape - Group","hd":false},{"ty":"fl","c":{"a":0,"k":[0.101960785687,0.090196080506,0.105882354081,1],"ix":4},"o":{"a":0,"k":100,"ix":5},"r":1,"bm":0,"nm":"Fill 1","mn":"ADBE Vector Graphic - Fill","hd":false},{"ty":"tr","p":{"a":0,"k":[0,0],"ix":2},"a":{"a":0,"k":[0,0],"ix":1},"s":{"a":0,"k":[100,100],"ix":3},"r":{"a":0,"k":0,"ix":6},"o":{"a":0,"k":100,"ix":7},"sk":{"a":0,"k":0,"ix":4},"sa":{"a":0,"k":0,"ix":5},"nm":"Transform"}],"nm":"Group 1","np":3,"cix":2,"bm":0,"ix":1,"mn":"ADBE Vector Group","hd":false}],"ip":0,"op":750,"st":0,"ct":1,"bm":0},{"ddd":0,"ind":5,"ty":4,"nm":"Isolation Mode","sr":1,"ks":{"o":{"a":0,"k":100,"ix":11},"r":{"a":0,"k":0,"ix":10},"p":{"a":1,"k":[{"i":{"x":0.667,"y":1},"o":{"x":0.333,"y":0},"t":0,"s":[255,257.633,0],"to":[0,-10.5,0],"ti":[0,0,0]},{"i":{"x":0.667,"y":1},"o":{"x":0.333,"y":0},"t":25,"s":[255,194.633,0],"to":[0,0,0],"ti":[0,-10.5,0]},{"t":50,"s":[255,257.633,0]}],"ix":2,"l":2,"x":"var $bm_rt;\n$bm_rt = loopOut();"},"a":{"a":0,"k":[5,7.633,0],"ix":1,"l":2},"s":{"a":1,"k":[{"i":{"x":[0.833,0.833,0.833],"y":[0.833,0.833,0.833]},"o":{"x":[0.167,0.167,0.167],"y":[0.167,0.167,0.167]},"t":0,"s":[0,0,100]},{"t":25,"s":[100,100,100]}],"ix":6,"l":2,"x":"var $bm_rt;\nfunction easeandwizz_outElastic(t, b, c, d, a, p) {\n    var s;\n    var p = 0.81;\n    var a = 50;\n    if (t == 0)\n        return b;\n    if ((t /= d) == 1)\n        return $bm_sum(b, c);\n    if (!p)\n        p = $bm_mul(d, 0.3);\n    if (!a || a < Math.abs(c)) {\n        a = c;\n        s = $bm_div(p, 4);\n    } else\n        s = $bm_mul($bm_div(p, $bm_mul(2, Math.PI)), Math.asin($bm_div(c, a)));\n    return $bm_sum($bm_sum($bm_mul($bm_mul(a, Math.pow(2, $bm_mul(-10, t))), Math.sin($bm_div($bm_mul($bm_sub($bm_mul(t, d), s), $bm_mul(2, Math.PI)), p))), c), b);\n}\nfunction easeAndWizz() {\n    var t, d, sX, eX, sY, eY, sZ, eZ, val1, val2, val2, val3;\n    var n = 0;\n    if (numKeys > 0) {\n        n = nearestKey(time).index;\n        if (key(n).time > time) {\n            n--;\n        }\n    }\n    try {\n        var key1 = key(n);\n        var key2 = key($bm_sum(n, 1));\n    } catch (e) {\n        return null;\n    }\n    var dim = 1;\n    try {\n        key(1)[1].length;\n        dim = 2;\n        key(1)[2].length;\n        dim = 3;\n    } catch (e) {\n    }\n    t = $bm_sub(time, key1.time);\n    d = $bm_sub(key2.time, key1.time);\n    sX = key1[0];\n    eX = $bm_sub(key2[0], key1[0]);\n    if (dim >= 2) {\n        sY = key1[1];\n        eY = $bm_sub(key2[1], key1[1]);\n        if (dim >= 3) {\n            sZ = key1[2];\n            eZ = $bm_sub(key2[2], key1[2]);\n        }\n    }\n    if (time < key1.time || time > key2.time) {\n        return value;\n    } else {\n        val1 = easeandwizz_outElastic(t, sX, eX, d);\n        switch (dim) {\n        case 1:\n            return val1;\n            break;\n        case 2:\n            val2 = easeandwizz_outElastic(t, sY, eY, d);\n            return [\n                val1,\n                val2\n            ];\n            break;\n        case 3:\n            val2 = easeandwizz_outElastic(t, sY, eY, d);\n            val3 = easeandwizz_outElastic(t, sZ, eZ, d);\n            return [\n                val1,\n                val2,\n                val3\n            ];\n            break;\n        default:\n            return null;\n        }\n    }\n}\n$bm_rt = easeAndWizz() || value;"}},"ao":0,"ef":[{"ty":21,"nm":"Fill","np":9,"mn":"ADBE Fill","ix":1,"en":1,"ef":[{"ty":10,"nm":"Fill Mask","mn":"ADBE Fill-0001","ix":1,"v":{"a":0,"k":0,"ix":1}},{"ty":7,"nm":"All Masks","mn":"ADBE Fill-0007","ix":2,"v":{"a":0,"k":0,"ix":2}},{"ty":2,"nm":"Color","mn":"ADBE Fill-0002","ix":3,"v":{"a":0,"k":[1,1,1,1],"ix":3,"x":"var $bm_rt;\n$bm_rt = thisComp.layer('CONTROLS').effect('Color_2')('ADBE Color Control-0001');"}},{"ty":7,"nm":"Invert","mn":"ADBE Fill-0006","ix":4,"v":{"a":0,"k":0,"ix":4}},{"ty":0,"nm":"Horizontal Feather","mn":"ADBE Fill-0003","ix":5,"v":{"a":0,"k":0,"ix":5}},{"ty":0,"nm":"Vertical Feather","mn":"ADBE Fill-0004","ix":6,"v":{"a":0,"k":0,"ix":6}},{"ty":0,"nm":"Opacity","mn":"ADBE Fill-0005","ix":7,"v":{"a":0,"k":1,"ix":7}}]}],"shapes":[{"ty":"gr","it":[{"ind":0,"ty":"sh","ix":1,"ks":{"a":0,"k":{"i":[[0,0],[0,0],[0,0],[20.48,-5.148],[0,0],[0,0]],"o":[[0,0],[0,0],[-0.159,6.216],[0,0],[0,0],[0,0]],"v":[[86.165,-73.604],[86.165,-73.604],[86.165,-68.934],[54.018,-49.633],[54.018,-74.082],[86.165,-81.397]],"c":true},"ix":2},"nm":"Path 2","mn":"ADBE Vector Shape - Group","hd":false},{"ind":1,"ty":"sh","ix":2,"ks":{"a":0,"k":{"i":[[13.93,-4.813],[4.367,1.243],[0,0],[-7.618,5.61],[0,0]],"o":[[-2.343,-3.73],[0,0],[13.165,-3.124],[0,0],[0,5.291]],"v":[[64.377,-20.386],[54.018,-28.164],[54.018,-39.05],[86.165,-52.135],[86.165,-36.563]],"c":true},"ix":2},"nm":"Path 3","mn":"ADBE Vector Shape - Group","hd":false},{"ind":2,"ty":"sh","ix":3,"ks":{"a":0,"k":{"i":[[4.367,0],[0,4.351],[-4.271,0],[0,-4.367]],"o":[[-4.271,0],[0,-4.367],[4.367,0],[0,4.351]],"v":[[48.726,-2.791],[40.869,-10.728],[48.726,-18.665],[56.6,-10.728]],"c":true},"ix":2},"nm":"Path 4","mn":"ADBE Vector Shape - Group","hd":false},{"ind":3,"ty":"sh","ix":4,"ks":{"a":0,"k":{"i":[[0,10.424],[0,0],[-31.749,0],[-12.209,2.024],[0,0],[0.924,-7.172],[9.26,0]],"o":[[0,0],[16.337,11.985],[13.005,0],[0,0],[-6.774,2.024],[-7.873,0.924],[-50.269,0]],"v":[[-76.165,-36.563],[-76.165,-52.135],[4.992,-33.758],[43.514,-36.882],[43.514,-28.164],[30.684,-13.214],[4.992,-11.812]],"c":true},"ix":2},"nm":"Path 5","mn":"ADBE Vector Shape - Group","hd":false},{"ind":4,"ty":"sh","ix":5,"ks":{"a":0,"k":{"i":[[0,0],[-0.383,0],[-0.398,0.159],[0,0],[0,0],[14.551,0],[0,10.424],[0,0],[0,0]],"o":[[0.383,0.159],[0.398,0],[0,0],[0,0],[-11.045,2.024],[-50.269,0],[0,0],[0,0],[0,0]],"v":[[3.829,-63.18],[4.992,-63.021],[6.171,-63.18],[43.514,-71.739],[43.514,-47.465],[4.992,-44.198],[-76.165,-69.093],[-76.165,-72.201],[-76.165,-81.397]],"c":true},"ix":2},"nm":"Path 6","mn":"ADBE Vector Shape - Group","hd":false},{"ind":5,"ty":"sh","ix":6,"ks":{"a":0,"k":{"i":[[2.407,0.622],[0,0],[0.781,-0.319],[0,0],[0,-2.486],[-2.423,-0.622],[0,0],[0,0],[0,0],[0,0],[-44.435,0],[-8.941,1.1],[-7.316,0],[-0.319,9.961],[0.08,11.683],[0,0],[0,0],[0,0],[0,0],[0,2.486]],"o":[[0,0],[-0.781,-0.319],[0,0],[-2.423,0.622],[0,2.486],[0,0],[0,0],[0,0],[0,0],[0,22.871],[9.117,0],[2.964,6.232],[9.961,0],[17.5,-5.913],[0,0],[0,0],[0,0],[0,0],[2.407,-0.622],[0,-2.486]],"v":[[173.952,-111.584],[6.171,-149.564],[3.829,-149.564],[-163.952,-111.584],[-168,-106.452],[-163.952,-101.32],[-86.684,-83.724],[-86.684,-75.628],[-86.684,-69.093],[-86.684,-36.563],[4.992,-1.229],[32.23,-2.95],[48.726,7.633],[67.103,-10.266],[96.588,-36.882],[96.588,-69.412],[96.588,-79.214],[96.588,-83.724],[173.952,-101.32],[178,-106.452]],"c":true},"ix":2},"nm":"Path 7","mn":"ADBE Vector Shape - Group","hd":false},{"ty":"fl","c":{"a":0,"k":[0.101960785687,0.090196080506,0.105882354081,1],"ix":4},"o":{"a":0,"k":100,"ix":5},"r":1,"bm":0,"nm":"Fill 1","mn":"ADBE Vector Graphic - Fill","hd":false},{"ty":"tr","p":{"a":0,"k":[0,0],"ix":2},"a":{"a":0,"k":[0,0],"ix":1},"s":{"a":0,"k":[100,100],"ix":3},"r":{"a":0,"k":0,"ix":6},"o":{"a":0,"k":100,"ix":7},"sk":{"a":0,"k":0,"ix":4},"sa":{"a":0,"k":0,"ix":5},"nm":"Transform"}],"nm":"Group 1","np":7,"cix":2,"bm":0,"ix":1,"mn":"ADBE Vector Group","hd":false}],"ip":0,"op":750,"st":0,"ct":1,"bm":0}],"markers":[]}